setup.cfg
setup.py
streamscrobbler/__init__.py
streamscrobbler/streamscrobbler.py
streamscrobbler.egg-info/PKG-INFO
streamscrobbler.egg-info/SOURCES.txt
streamscrobbler.egg-info/dependency_links.txt
streamscrobbler.egg-info/requires.txt
streamscrobbler.egg-info/top_level.txt