Metadata-Version: 1.0
Name: streamscrobbler
Version: 0.0.1
Summary: A python class used on Dirble.com to get titles and bitrates on shoutcast and icecast streams
Home-page: https://github.com/Dirble/streamscrobbler-python
Author: Håkan Nylén
Author-email: confacted@gmail.com
License: UNKNOWN
Keywords: shoutcast,icecast,stream,ICY
Platform: UNKNOWN
